{
  "__inputs": [
    {
      "name": "DS_PROMETHEUS",
      "label": "prometheus",
      "description": "",
      "type": "datasource",
      "pluginId": "prometheus",
      "pluginName": "Prometheus"
    }
  ],
  "__elements": {},
  "__requires": [
    {
      "type": "grafana",
      "id": "grafana",
      "name": "Grafana",
      "version": "11.4.0"
    },
    {
      "type": "datasource",
      "id": "prometheus",
      "name": "Prometheus",
      "version": "1.0.0"
    },
    {
      "type": "panel",
      "id": "stat",
      "name": "Stat",
      "version": ""
    },
    {
      "type": "panel",
      "id": "state-timeline",
      "name": "State timeline",
      "version": ""
    },
    {
      "type": "panel",
      "id": "timeseries",
      "name": "Time series",
      "version": ""
    }
  ],
  "annotations": {
    "list": [
      {
        "builtIn": 1,
        "datasource": {
          "type": "grafana",
          "uid": "-- Grafana --"
        },
        "enable": true,
        "hide": true,
        "iconColor": "rgba(0, 211, 255, 1)",
        "name": "Annotations & Alerts",
        "type": "dashboard"
      }
    ]
  },
  "description": "Example sfptpd Grafana dashboard.\n© Copyright 2025, Advanced Micro Devices, Inc.\nLicense: BSD-3-Clause",
  "editable": true,
  "fiscalYearStartMonth": 0,
  "graphTooltip": 0,
  "id": null,
  "links": [],
  "panels": [
    {
      "datasource": {
        "type": "prometheus",
        "uid": "${DS_PROMETHEUS}"
      },
      "fieldConfig": {
        "defaults": {
          "color": {
            "mode": "thresholds"
          },
          "mappings": [],
          "thresholds": {
            "mode": "absolute",
            "steps": [
              {
                "color": "dark-red",
                "value": null
              },
              {
                "color": "semi-dark-green",
                "value": 1
              }
            ]
          },
          "unit": "bool_yes_no"
        },
        "overrides": []
      },
      "gridPos": {
        "h": 4,
        "w": 24,
        "x": 0,
        "y": 0
      },
      "id": 7,
      "maxPerRow": 6,
      "options": {
        "colorMode": "background_solid",
        "graphMode": "area",
        "justifyMode": "auto",
        "orientation": "auto",
        "percentChangeColorMode": "standard",
        "reduceOptions": {
          "calcs": [
            "lastNotNull"
          ],
          "fields": "",
          "values": false
        },
        "showPercentChange": false,
        "textMode": "value_and_name",
        "wideLayout": false
      },
      "pluginVersion": "11.4.0",
      "repeat": "SyncInstance",
      "repeatDirection": "h",
      "targets": [
        {
          "disableTextWrap": false,
          "editorMode": "builder",
          "expr": "in_sync{instance=\"$Source\"}",
          "fullMetaSearch": false,
          "includeNullMetadata": true,
          "legendFormat": "__auto",
          "range": true,
          "refId": "A",
          "useBackend": false,
          "datasource": {
            "type": "prometheus",
            "uid": "${DS_PROMETHEUS}"
          }
        }
      ],
      "title": "In sync",
      "transformations": [
        {
          "id": "labelsToFields",
          "options": {
            "keepLabels": [
              "sync"
            ],
            "valueLabel": "sync"
          }
        }
      ],
      "type": "stat"
    },
    {
      "datasource": {
        "type": "prometheus",
        "uid": "${DS_PROMETHEUS}"
      },
      "fieldConfig": {
        "defaults": {
          "color": {
            "mode": "thresholds"
          },
          "mappings": [],
          "thresholds": {
            "mode": "absolute",
            "steps": [
              {
                "color": "light-blue",
                "value": null
              },
              {
                "color": "light-orange",
                "value": 80
              }
            ]
          },
          "unit": "bool_yes_no"
        },
        "overrides": []
      },
      "gridPos": {
        "h": 4,
        "w": 24,
        "x": 0,
        "y": 4
      },
      "id": 8,
      "maxPerRow": 8,
      "options": {
        "colorMode": "value",
        "graphMode": "area",
        "justifyMode": "auto",
        "orientation": "auto",
        "percentChangeColorMode": "standard",
        "reduceOptions": {
          "calcs": [
            "lastNotNull"
          ],
          "fields": "",
          "values": false
        },
        "showPercentChange": false,
        "textMode": "value_and_name",
        "wideLayout": false
      },
      "pluginVersion": "11.4.0",
      "repeat": "Instances",
      "repeatDirection": "h",
      "targets": [
        {
          "disableTextWrap": false,
          "editorMode": "builder",
          "expr": "is_disciplining{instance=\"$Source\"}",
          "fullMetaSearch": false,
          "includeNullMetadata": true,
          "legendFormat": "__auto",
          "range": true,
          "refId": "A",
          "useBackend": false,
          "datasource": {
            "type": "prometheus",
            "uid": "${DS_PROMETHEUS}"
          }
        }
      ],
      "title": "Disciplining",
      "transformations": [
        {
          "id": "labelsToFields",
          "options": {
            "keepLabels": [
              "sync"
            ],
            "valueLabel": "sync"
          }
        }
      ],
      "type": "stat"
    },
    {
      "datasource": {
        "type": "prometheus",
        "uid": "${DS_PROMETHEUS}"
      },
      "fieldConfig": {
        "defaults": {
          "color": {
            "mode": "thresholds"
          },
          "mappings": [],
          "thresholds": {
            "mode": "absolute",
            "steps": [
              {
                "color": "green",
                "value": null
              },
              {
                "color": "red",
                "value": 80
              }
            ]
          }
        },
        "overrides": []
      },
      "gridPos": {
        "h": 4,
        "w": 24,
        "x": 0,
        "y": 8
      },
      "id": 6,
      "maxPerRow": 8,
      "options": {
        "colorMode": "value",
        "graphMode": "area",
        "justifyMode": "auto",
        "orientation": "auto",
        "percentChangeColorMode": "standard",
        "reduceOptions": {
          "calcs": [
            "lastNotNull"
          ],
          "fields": "",
          "values": false
        },
        "showPercentChange": false,
        "textMode": "value_and_name",
        "wideLayout": false
      },
      "pluginVersion": "11.4.0",
      "repeat": "SyncInstance",
      "repeatDirection": "h",
      "targets": [
        {
          "disableTextWrap": false,
          "editorMode": "builder",
          "expr": "alarms{instance=\"$Source\"}",
          "fullMetaSearch": false,
          "includeNullMetadata": true,
          "legendFormat": "__auto",
          "range": true,
          "refId": "A",
          "useBackend": false,
          "datasource": {
            "type": "prometheus",
            "uid": "${DS_PROMETHEUS}"
          }
        }
      ],
      "title": "Alarms",
      "transformations": [
        {
          "id": "labelsToFields",
          "options": {
            "valueLabel": "sync"
          }
        }
      ],
      "type": "stat"
    },
    {
      "datasource": {
        "type": "prometheus",
        "uid": "${DS_PROMETHEUS}"
      },
      "fieldConfig": {
        "defaults": {
          "color": {
            "mode": "thresholds"
          },
          "mappings": [],
          "thresholds": {
            "mode": "absolute",
            "steps": [
              {
                "color": "dark-green",
                "value": null
              }
            ]
          },
          "unit": "dateTimeFromNow"
        },
        "overrides": []
      },
      "gridPos": {
        "h": 4,
        "w": 24,
        "x": 0,
        "y": 12
      },
      "id": 11,
      "maxPerRow": 4,
      "options": {
        "colorMode": "none",
        "graphMode": "none",
        "justifyMode": "auto",
        "orientation": "auto",
        "percentChangeColorMode": "standard",
        "reduceOptions": {
          "calcs": [
            "lastNotNull"
          ],
          "fields": "",
          "values": false
        },
        "showPercentChange": false,
        "textMode": "value_and_name",
        "wideLayout": false
      },
      "pluginVersion": "11.4.0",
      "repeat": "SyncInstance",
      "repeatDirection": "h",
      "targets": [
        {
          "disableTextWrap": false,
          "editorMode": "code",
          "expr": "last_update_seconds*1000",
          "fullMetaSearch": false,
          "includeNullMetadata": true,
          "legendFormat": "__auto",
          "range": true,
          "refId": "A",
          "useBackend": false,
          "datasource": {
            "type": "prometheus",
            "uid": "${DS_PROMETHEUS}"
          }
        }
      ],
      "title": "Last update",
      "transformations": [
        {
          "id": "labelsToFields",
          "options": {
            "valueLabel": "sync"
          }
        },
        {
          "id": "filterByValue",
          "options": {
            "filters": [
              {
                "config": {
                  "id": "equal",
                  "options": {
                    "value": "${Source}"
                  }
                },
                "fieldName": "instance"
              }
            ],
            "match": "any",
            "type": "include"
          }
        }
      ],
      "type": "stat"
    },
    {
      "collapsed": false,
      "gridPos": {
        "h": 1,
        "w": 24,
        "x": 0,
        "y": 16
      },
      "id": 9,
      "panels": [],
      "title": "Stats",
      "type": "row"
    },
    {
      "datasource": {
        "type": "prometheus",
        "uid": "${DS_PROMETHEUS}"
      },
      "fieldConfig": {
        "defaults": {
          "color": {
            "mode": "palette-classic"
          },
          "custom": {
            "axisBorderShow": false,
            "axisCenteredZero": false,
            "axisColorMode": "text",
            "axisLabel": "",
            "axisPlacement": "auto",
            "barAlignment": 0,
            "barWidthFactor": 0.6,
            "drawStyle": "line",
            "fillOpacity": 0,
            "gradientMode": "none",
            "hideFrom": {
              "legend": false,
              "tooltip": false,
              "viz": false
            },
            "insertNulls": false,
            "lineInterpolation": "linear",
            "lineWidth": 1,
            "pointSize": 5,
            "scaleDistribution": {
              "type": "linear"
            },
            "showPoints": "auto",
            "spanNulls": false,
            "stacking": {
              "group": "A",
              "mode": "none"
            },
            "thresholdsStyle": {
              "mode": "off"
            }
          },
          "mappings": [],
          "thresholds": {
            "mode": "absolute",
            "steps": [
              {
                "color": "green",
                "value": null
              },
              {
                "color": "red",
                "value": 80
              }
            ]
          },
          "unit": "s"
        },
        "overrides": []
      },
      "gridPos": {
        "h": 18,
        "w": 14,
        "x": 0,
        "y": 17
      },
      "id": 1,
      "interval": "0.0625s",
      "options": {
        "legend": {
          "calcs": [],
          "displayMode": "list",
          "placement": "bottom",
          "showLegend": true
        },
        "tooltip": {
          "mode": "single",
          "sort": "none"
        }
      },
      "pluginVersion": "11.4.0",
      "targets": [
        {
          "datasource": {
            "type": "prometheus",
            "uid": "${DS_PROMETHEUS}"
          },
          "disableTextWrap": false,
          "editorMode": "builder",
          "expr": "offset_seconds",
          "fullMetaSearch": false,
          "includeNullMetadata": true,
          "legendFormat": "{{instance}}/{{sync}}",
          "range": true,
          "refId": "A",
          "useBackend": false
        }
      ],
      "title": "Offset",
      "type": "timeseries"
    },
    {
      "datasource": {
        "type": "prometheus",
        "uid": "${DS_PROMETHEUS}"
      },
      "fieldConfig": {
        "defaults": {
          "color": {
            "mode": "palette-classic"
          },
          "custom": {
            "axisBorderShow": false,
            "axisCenteredZero": false,
            "axisColorMode": "text",
            "axisLabel": "",
            "axisPlacement": "auto",
            "barAlignment": 0,
            "barWidthFactor": 0.6,
            "drawStyle": "line",
            "fillOpacity": 0,
            "gradientMode": "none",
            "hideFrom": {
              "legend": false,
              "tooltip": false,
              "viz": false
            },
            "insertNulls": false,
            "lineInterpolation": "linear",
            "lineWidth": 1,
            "pointSize": 5,
            "scaleDistribution": {
              "type": "linear"
            },
            "showPoints": "auto",
            "spanNulls": false,
            "stacking": {
              "group": "A",
              "mode": "none"
            },
            "thresholdsStyle": {
              "mode": "off"
            }
          },
          "mappings": [],
          "thresholds": {
            "mode": "absolute",
            "steps": [
              {
                "color": "green",
                "value": null
              },
              {
                "color": "red",
                "value": 80
              }
            ]
          },
          "unit": "ppb"
        },
        "overrides": []
      },
      "gridPos": {
        "h": 9,
        "w": 6,
        "x": 14,
        "y": 17
      },
      "id": 2,
      "interval": "0.0625s",
      "options": {
        "legend": {
          "calcs": [],
          "displayMode": "list",
          "placement": "bottom",
          "showLegend": true
        },
        "tooltip": {
          "mode": "single",
          "sort": "none"
        }
      },
      "pluginVersion": "11.4.0",
      "targets": [
        {
          "disableTextWrap": false,
          "editorMode": "builder",
          "expr": "freq_adj_ratios",
          "fullMetaSearch": false,
          "includeNullMetadata": true,
          "legendFormat": "{{instance}}/{{sync}}",
          "range": true,
          "refId": "A",
          "useBackend": false,
          "datasource": {
            "type": "prometheus",
            "uid": "${DS_PROMETHEUS}"
          }
        }
      ],
      "title": "Frequency adjustment",
      "type": "timeseries"
    },
    {
      "datasource": {
        "type": "prometheus",
        "uid": "${DS_PROMETHEUS}"
      },
      "fieldConfig": {
        "defaults": {
          "color": {
            "mode": "palette-classic"
          },
          "custom": {
            "axisBorderShow": false,
            "axisCenteredZero": false,
            "axisColorMode": "text",
            "axisLabel": "i-term",
            "axisPlacement": "auto",
            "barAlignment": 0,
            "barWidthFactor": 0.6,
            "drawStyle": "line",
            "fillOpacity": 22,
            "gradientMode": "none",
            "hideFrom": {
              "legend": false,
              "tooltip": false,
              "viz": false
            },
            "insertNulls": false,
            "lineInterpolation": "linear",
            "lineWidth": 0,
            "pointSize": 5,
            "scaleDistribution": {
              "type": "linear"
            },
            "showPoints": "auto",
            "spanNulls": false,
            "stacking": {
              "group": "A",
              "mode": "none"
            },
            "thresholdsStyle": {
              "mode": "off"
            }
          },
          "mappings": [],
          "thresholds": {
            "mode": "absolute",
            "steps": [
              {
                "color": "green",
                "value": null
              },
              {
                "color": "red",
                "value": 80
              }
            ]
          }
        },
        "overrides": [
          {
            "matcher": {
              "id": "byName",
              "options": "pterm_ratios"
            },
            "properties": [
              {
                "id": "custom.axisPlacement",
                "value": "right"
              },
              {
                "id": "custom.axisLabel",
                "value": "p-term"
              },
              {
                "id": "custom.fillOpacity",
                "value": 0
              },
              {
                "id": "custom.lineWidth",
                "value": 1
              }
            ]
          }
        ]
      },
      "gridPos": {
        "h": 8,
        "w": 6,
        "x": 14,
        "y": 26
      },
      "id": 3,
      "interval": "0.0625s",
      "options": {
        "legend": {
          "calcs": [],
          "displayMode": "list",
          "placement": "bottom",
          "showLegend": true
        },
        "tooltip": {
          "mode": "single",
          "sort": "none"
        }
      },
      "pluginVersion": "11.4.0",
      "targets": [
        {
          "disableTextWrap": false,
          "editorMode": "builder",
          "expr": "iterm_ratios",
          "fullMetaSearch": false,
          "includeNullMetadata": true,
          "legendFormat": "{{instance}}/{{sync}}/I",
          "range": true,
          "refId": "A",
          "useBackend": false,
          "datasource": {
            "type": "prometheus",
            "uid": "${DS_PROMETHEUS}"
          }
        },
        {
          "datasource": {
            "type": "prometheus",
            "uid": "${DS_PROMETHEUS}"
          },
          "disableTextWrap": false,
          "editorMode": "builder",
          "expr": "pterm_ratios",
          "fullMetaSearch": false,
          "hide": false,
          "includeNullMetadata": true,
          "instant": false,
          "legendFormat": "{{instance}}/{{sync}}/P",
          "range": true,
          "refId": "B",
          "useBackend": false
        }
      ],
      "title": "P Term (line); I term (filled)",
      "type": "timeseries"
    },
    {
      "datasource": {
        "type": "prometheus",
        "uid": "${DS_PROMETHEUS}"
      },
      "fieldConfig": {
        "defaults": {
          "color": {
            "mode": "palette-classic"
          },
          "custom": {
            "axisBorderShow": false,
            "axisCenteredZero": false,
            "axisColorMode": "text",
            "axisLabel": "",
            "axisPlacement": "auto",
            "barAlignment": 0,
            "barWidthFactor": 0.6,
            "drawStyle": "line",
            "fillOpacity": 0,
            "gradientMode": "none",
            "hideFrom": {
              "legend": false,
              "tooltip": false,
              "viz": false
            },
            "insertNulls": false,
            "lineInterpolation": "linear",
            "lineWidth": 1,
            "pointSize": 5,
            "scaleDistribution": {
              "type": "linear"
            },
            "showPoints": "auto",
            "spanNulls": false,
            "stacking": {
              "group": "A",
              "mode": "none"
            },
            "thresholdsStyle": {
              "mode": "off"
            }
          },
          "mappings": [],
          "thresholds": {
            "mode": "absolute",
            "steps": [
              {
                "color": "green",
                "value": null
              },
              {
                "color": "red",
                "value": 80
              }
            ]
          },
          "unit": "s"
        },
        "overrides": []
      },
      "gridPos": {
        "h": 6,
        "w": 6,
        "x": 14,
        "y": 34
      },
      "id": 10,
      "options": {
        "legend": {
          "calcs": [],
          "displayMode": "list",
          "placement": "bottom",
          "showLegend": true
        },
        "tooltip": {
          "mode": "single",
          "sort": "none"
        }
      },
      "pluginVersion": "11.4.0",
      "targets": [
        {
          "disableTextWrap": false,
          "editorMode": "code",
          "expr": "owd_seconds",
          "fullMetaSearch": false,
          "includeNullMetadata": true,
          "legendFormat": "{{instance}}/{{sync}}",
          "range": true,
          "refId": "A",
          "useBackend": false,
          "datasource": {
            "type": "prometheus",
            "uid": "${DS_PROMETHEUS}"
          }
        }
      ],
      "title": "One way delay",
      "type": "timeseries"
    },
    {
      "datasource": {
        "type": "prometheus",
        "uid": "${DS_PROMETHEUS}"
      },
      "fieldConfig": {
        "defaults": {
          "color": {
            "mode": "fixed"
          },
          "custom": {
            "fillOpacity": 70,
            "hideFrom": {
              "legend": false,
              "tooltip": false,
              "viz": false
            },
            "insertNulls": false,
            "lineWidth": 0,
            "spanNulls": false
          },
          "mappings": [
            {
              "options": {
                "none": {
                  "color": "dark-green",
                  "index": 0
                }
              },
              "type": "value"
            }
          ],
          "thresholds": {
            "mode": "absolute",
            "steps": [
              {
                "color": "dark-red",
                "value": null
              },
              {
                "color": "red",
                "value": 80
              }
            ]
          }
        },
        "overrides": []
      },
      "gridPos": {
        "h": 5,
        "w": 12,
        "x": 0,
        "y": 35
      },
      "id": 5,
      "options": {
        "alignValue": "center",
        "legend": {
          "displayMode": "list",
          "placement": "bottom",
          "showLegend": true
        },
        "mergeValues": true,
        "rowHeight": 0.9,
        "showValue": "always",
        "tooltip": {
          "mode": "single",
          "sort": "none"
        }
      },
      "pluginVersion": "11.4.0",
      "repeatDirection": "h",
      "targets": [
        {
          "disableTextWrap": false,
          "editorMode": "builder",
          "expr": "alarmtxt",
          "fullMetaSearch": false,
          "includeNullMetadata": true,
          "legendFormat": "__auto",
          "range": true,
          "refId": "A",
          "useBackend": false,
          "datasource": {
            "type": "prometheus",
            "uid": "${DS_PROMETHEUS}"
          }
        }
      ],
      "title": "Alarms",
      "transformations": [
        {
          "id": "labelsToFields",
          "options": {
            "keepLabels": [
              "alarms",
              "sync"
            ],
            "mode": "columns"
          }
        },
        {
          "id": "partitionByValues",
          "options": {
            "fields": [
              "sync"
            ],
            "keepFields": false,
            "naming": {
              "asLabels": true
            }
          }
        },
        {
          "id": "filterFieldsByName",
          "options": {
            "include": {
              "names": [
                "Time servo0",
                "alarms servo0"
              ]
            }
          }
        }
      ],
      "type": "state-timeline"
    },
    {
      "datasource": {
        "type": "prometheus",
        "uid": "${DS_PROMETHEUS}"
      },
      "fieldConfig": {
        "defaults": {
          "color": {
            "mode": "thresholds"
          },
          "mappings": [],
          "thresholds": {
            "mode": "absolute",
            "steps": [
              {
                "color": "green",
                "value": null
              },
              {
                "color": "red",
                "value": 80
              }
            ]
          }
        },
        "overrides": []
      },
      "gridPos": {
        "h": 5,
        "w": 2,
        "x": 12,
        "y": 35
      },
      "id": 12,
      "options": {
        "colorMode": "value",
        "graphMode": "area",
        "justifyMode": "auto",
        "orientation": "auto",
        "percentChangeColorMode": "standard",
        "reduceOptions": {
          "calcs": [
            "lastNotNull"
          ],
          "fields": "",
          "values": false
        },
        "showPercentChange": false,
        "textMode": "auto",
        "wideLayout": true
      },
      "pluginVersion": "11.4.0",
      "targets": [
        {
          "disableTextWrap": false,
          "editorMode": "builder",
          "expr": "lost_rt",
          "fullMetaSearch": false,
          "includeNullMetadata": true,
          "legendFormat": "__auto",
          "range": true,
          "refId": "A",
          "useBackend": false,
          "datasource": {
            "type": "prometheus",
            "uid": "${DS_PROMETHEUS}"
          }
        }
      ],
      "title": "Lost RT samples",
      "type": "stat"
    }
  ],
  "schemaVersion": 40,
  "tags": [],
  "templating": {
    "list": [
      {
        "current": {},
        "definition": "label_values(instance)",
        "name": "Source",
        "options": [],
        "query": {
          "qryType": 1,
          "query": "label_values(instance)",
          "refId": "PrometheusVariableQueryEditor-VariableQuery"
        },
        "refresh": 1,
        "regex": "",
        "type": "query"
      },
      {
        "current": {},
        "definition": "label_values(sync)",
        "name": "SyncInstance",
        "options": [],
        "query": {
          "qryType": 1,
          "query": "label_values(sync)",
          "refId": "PrometheusVariableQueryEditor-VariableQuery"
        },
        "refresh": 1,
        "regex": "",
        "type": "query"
      }
    ]
  },
  "time": {
    "from": "now-30m",
    "to": "now"
  },
  "timepicker": {},
  "timezone": "browser",
  "title": "sfptpd",
  "uid": "fear2igzdbmkgb",
  "version": 27,
  "weekStart": ""
}